{
  "formatVersion": 1,
  "database": {
    "version": 2,
    "identityHash": "c362960db95b2ae4034c3ac082d47e47",
    "entities": [
      {
        "tableName": "projects",
        "createSql": "CREATE TABLE IF NOT EXISTS `${TABLE_NAME}` (`id` TEXT NOT NULL, `name` TEXT NOT NULL, `description` TEXT, `sport_type` TEXT NOT NULL, `created_at` INTEGER NOT NULL, `updated_at` INTEGER NOT NULL, `thumbnail_path` TEXT, `resolution_width` INTEGER NOT NULL, `resolution_height` INTEGER NOT NULL, `frame_rate` INTEGER NOT NULL, `export_format` TEXT NOT NULL, `bitrate_bps` INTEGER NOT NULL, `audio_codec` TEXT NOT NULL, `template_id` TEXT, PRIMARY KEY(`id`))",
        "fields": [
          {
            "fieldPath": "id",
            "columnName": "id",
            "affinity": "TEXT",
            "notNull": true
          },
          {
            "fieldPath": "name",
            "columnName": "name",
            "affinity": "TEXT",
            "notNull": true
          },
          {
            "fieldPath": "description",
            "columnName": "description",
            "affinity": "TEXT"
          },
          {
            "fieldPath": "sportType",
            "columnName": "sport_type",
            "affinity": "TEXT",
            "notNull": true
          },
          {
            "fieldPath": "createdAt",
            "columnName": "created_at",
            "affinity": "INTEGER",
            "notNull": true
          },
          {
            "fieldPath": "updatedAt",
            "columnName": "updated_at",
            "affinity": "INTEGER",
            "notNull": true
          },
          {
            "fieldPath": "thumbnailPath",
            "columnName": "thumbnail_path",
            "affinity": "TEXT"
          },
          {
            "fieldPath": "resolutionWidth",
            "columnName": "resolution_width",
            "affinity": "INTEGER",
            "notNull": true
          },
          {
            "fieldPath": "resolutionHeight",
            "columnName": "resolution_height",
            "affinity": "INTEGER",
            "notNull": true
          },
          {
            "fieldPath": "frameRate",
            "columnName": "frame_rate",
            "affinity": "INTEGER",
            "notNull": true
          },
          {
            "fieldPath": "exportFormat",
            "columnName": "export_format",
            "affinity": "TEXT",
            "notNull": true
          },
          {
            "fieldPath": "bitrateBps",
            "columnName": "bitrate_bps",
            "affinity": "INTEGER",
            "notNull": true
          },
          {
            "fieldPath": "audioCodec",
            "columnName": "audio_codec",
            "affinity": "TEXT",
            "notNull": true
          },
          {
            "fieldPath": "templateId",
            "columnName": "template_id",
            "affinity": "TEXT"
          }
        ],
        "primaryKey": {
          "autoGenerate": false,
          "columnNames": [
            "id"
          ]
        }
      },
      {
        "tableName": "media_items",
        "createSql": "CREATE TABLE IF NOT EXISTS `${TABLE_NAME}` (`id` TEXT NOT NULL, `project_id` TEXT NOT NULL, `type` TEXT NOT NULL, `source_path` TEXT NOT NULL, `local_copy_path` TEXT NOT NULL, `duration_ms` INTEGER, `width` INTEGER NOT NULL, `height` INTEGER NOT NULL, `rotation` INTEGER NOT NULL, `created_at` INTEGER NOT NULL, `codec` TEXT, `bitrate` INTEGER, `file_size` INTEGER NOT NULL, `has_audio` INTEGER NOT NULL, `audio_codec` TEXT, `gps_latitude` REAL, `gps_longitude` REAL, PRIMARY KEY(`id`), FOREIGN KEY(`project_id`) REFERENCES `projects`(`id`) ON UPDATE NO ACTION ON DELETE CASCADE )",
        "fields": [
          {
            "fieldPath": "id",
            "columnName": "id",
            "affinity": "TEXT",
            "notNull": true
          },
          {
            "fieldPath": "projectId",
            "columnName": "project_id",
            "affinity": "TEXT",
            "notNull": true
          },
          {
            "fieldPath": "type",
            "columnName": "type",
            "affinity": "TEXT",
            "notNull": true
          },
          {
            "fieldPath": "sourcePath",
            "columnName": "source_path",
            "affinity": "TEXT",
            "notNull": true
          },
          {
            "fieldPath": "localCopyPath",
            "columnName": "local_copy_path",
            "affinity": "TEXT",
            "notNull": true
          },
          {
            "fieldPath": "durationMs",
            "columnName": "duration_ms",
            "affinity": "INTEGER"
          },
          {
            "fieldPath": "width",
            "columnName": "width",
            "affinity": "INTEGER",
            "notNull": true
          },
          {
            "fieldPath": "height",
            "columnName": "height",
            "affinity": "INTEGER",
            "notNull": true
          },
          {
            "fieldPath": "rotation",
            "columnName": "rotation",
            "affinity": "INTEGER",
            "notNull": true
          },
          {
            "fieldPath": "createdAt",
            "columnName": "created_at",
            "affinity": "INTEGER",
            "notNull": true
          },
          {
            "fieldPath": "codec",
            "columnName": "codec",
            "affinity": "TEXT"
          },
          {
            "fieldPath": "bitrate",
            "columnName": "bitrate",
            "affinity": "INTEGER"
          },
          {
            "fieldPath": "fileSize",
            "columnName": "file_size",
            "affinity": "INTEGER",
            "notNull": true
          },
          {
            "fieldPath": "hasAudio",
            "columnName": "has_audio",
            "affinity": "INTEGER",
            "notNull": true
          },
          {
            "fieldPath": "audioCodec",
            "columnName": "audio_codec",
            "affinity": "TEXT"
          },
          {
            "fieldPath": "gpsLatitude",
            "columnName": "gps_latitude",
            "affinity": "REAL"
          },
          {
            "fieldPath": "gpsLongitude",
            "columnName": "gps_longitude",
            "affinity": "REAL"
          }
        ],
        "primaryKey": {
          "autoGenerate": false,
          "columnNames": [
            "id"
          ]
        },
        "indices": [
          {
            "name": "index_media_items_project_id",
            "unique": false,
            "columnNames": [
              "project_id"
            ],
            "orders": [],
            "createSql": "CREATE INDEX IF NOT EXISTS `index_media_items_project_id` ON `${TABLE_NAME}` (`project_id`)"
          }
        ],
        "foreignKeys": [
          {
            "table": "projects",
            "onDelete": "CASCADE",
            "onUpdate": "NO ACTION",
            "columns": [
              "project_id"
            ],
            "referencedColumns": [
              "id"
            ]
          }
        ]
      },
      {
        "tableName": "gpx_files",
        "createSql": "CREATE TABLE IF NOT EXISTS `${TABLE_NAME}` (`id` TEXT NOT NULL, `project_id` TEXT NOT NULL, `name` TEXT NOT NULL, `file_path` TEXT NOT NULL, `parsed_data_json` TEXT, PRIMARY KEY(`id`), FOREIGN KEY(`project_id`) REFERENCES `projects`(`id`) ON UPDATE NO ACTION ON DELETE CASCADE )",
        "fields": [
          {
            "fieldPath": "id",
            "columnName": "id",
            "affinity": "TEXT",
            "notNull": true
          },
          {
            "fieldPath": "projectId",
            "columnName": "project_id",
            "affinity": "TEXT",
            "notNull": true
          },
          {
            "fieldPath": "name",
            "columnName": "name",
            "affinity": "TEXT",
            "notNull": true
          },
          {
            "fieldPath": "filePath",
            "columnName": "file_path",
            "affinity": "TEXT",
            "notNull": true
          },
          {
            "fieldPath": "parsedDataJson",
            "columnName": "parsed_data_json",
            "affinity": "TEXT"
          }
        ],
        "primaryKey": {
          "autoGenerate": false,
          "columnNames": [
            "id"
          ]
        },
        "indices": [
          {
            "name": "index_gpx_files_project_id",
            "unique": false,
            "columnNames": [
              "project_id"
            ],
            "orders": [],
            "createSql": "CREATE INDEX IF NOT EXISTS `index_gpx_files_project_id` ON `${TABLE_NAME}` (`project_id`)"
          }
        ],
        "foreignKeys": [
          {
            "table": "projects",
            "onDelete": "CASCADE",
            "onUpdate": "NO ACTION",
            "columns": [
              "project_id"
            ],
            "referencedColumns": [
              "id"
            ]
          }
        ]
      },
      {
        "tableName": "timeline_tracks",
        "createSql": "CREATE TABLE IF NOT EXISTS `${TABLE_NAME}` (`id` TEXT NOT NULL, `project_id` TEXT NOT NULL, `type` TEXT NOT NULL, `track_order` INTEGER NOT NULL, `is_locked` INTEGER NOT NULL, `is_visible` INTEGER NOT NULL, PRIMARY KEY(`id`), FOREIGN KEY(`project_id`) REFERENCES `projects`(`id`) ON UPDATE NO ACTION ON DELETE CASCADE )",
        "fields": [
          {
            "fieldPath": "id",
            "columnName": "id",
            "affinity": "TEXT",
            "notNull": true
          },
          {
            "fieldPath": "projectId",
            "columnName": "project_id",
            "affinity": "TEXT",
            "notNull": true
          },
          {
            "fieldPath": "type",
            "columnName": "type",
            "affinity": "TEXT",
            "notNull": true
          },
          {
            "fieldPath": "order",
            "columnName": "track_order",
            "affinity": "INTEGER",
            "notNull": true
          },
          {
            "fieldPath": "isLocked",
            "columnName": "is_locked",
            "affinity": "INTEGER",
            "notNull": true
          },
          {
            "fieldPath": "isVisible",
            "columnName": "is_visible",
            "affinity": "INTEGER",
            "notNull": true
          }
        ],
        "primaryKey": {
          "autoGenerate": false,
          "columnNames": [
            "id"
          ]
        },
        "indices": [
          {
            "name": "index_timeline_tracks_project_id",
            "unique": false,
            "columnNames": [
              "project_id"
            ],
            "orders": [],
            "createSql": "CREATE INDEX IF NOT EXISTS `index_timeline_tracks_project_id` ON `${TABLE_NAME}` (`project_id`)"
          }
        ],
        "foreignKeys": [
          {
            "table": "projects",
            "onDelete": "CASCADE",
            "onUpdate": "NO ACTION",
            "columns": [
              "project_id"
            ],
            "referencedColumns": [
              "id"
            ]
          }
        ]
      },
      {
        "tableName": "timeline_clips",
        "createSql": "CREATE TABLE IF NOT EXISTS `${TABLE_NAME}` (`id` TEXT NOT NULL, `track_id` TEXT NOT NULL, `media_item_id` TEXT, `start_time_ms` INTEGER NOT NULL, `end_time_ms` INTEGER NOT NULL, `trim_start_ms` INTEGER NOT NULL, `trim_end_ms` INTEGER NOT NULL, `entry_transition_type` TEXT, `entry_transition_duration_ms` INTEGER, `exit_transition_type` TEXT, `exit_transition_duration_ms` INTEGER, `content_mode` TEXT NOT NULL, `volume` REAL NOT NULL, `speed` REAL NOT NULL, `brightness` REAL NOT NULL, `contrast` REAL NOT NULL, `saturation` REAL NOT NULL, `rotation` REAL NOT NULL, `scale` REAL NOT NULL, `position_x` REAL NOT NULL, `position_y` REAL NOT NULL, `opacity` REAL NOT NULL, PRIMARY KEY(`id`), FOREIGN KEY(`track_id`) REFERENCES `timeline_tracks`(`id`) ON UPDATE NO ACTION ON DELETE CASCADE )",
        "fields": [
          {
            "fieldPath": "id",
            "columnName": "id",
            "affinity": "TEXT",
            "notNull": true
          },
          {
            "fieldPath": "trackId",
            "columnName": "track_id",
            "affinity": "TEXT",
            "notNull": true
          },
          {
            "fieldPath": "mediaItemId",
            "columnName": "media_item_id",
            "affinity": "TEXT"
          },
          {
            "fieldPath": "startTimeMs",
            "columnName": "start_time_ms",
            "affinity": "INTEGER",
            "notNull": true
          },
          {
            "fieldPath": "endTimeMs",
            "columnName": "end_time_ms",
            "affinity": "INTEGER",
            "notNull": true
          },
          {
            "fieldPath": "trimStartMs",
            "columnName": "trim_start_ms",
            "affinity": "INTEGER",
            "notNull": true
          },
          {
            "fieldPath": "trimEndMs",
            "columnName": "trim_end_ms",
            "affinity": "INTEGER",
            "notNull": true
          },
          {
            "fieldPath": "entryTransitionType",
            "columnName": "entry_transition_type",
            "affinity": "TEXT"
          },
          {
            "fieldPath": "entryTransitionDurationMs",
            "columnName": "entry_transition_duration_ms",
            "affinity": "INTEGER"
          },
          {
            "fieldPath": "exitTransitionType",
            "columnName": "exit_transition_type",
            "affinity": "TEXT"
          },
          {
            "fieldPath": "exitTransitionDurationMs",
            "columnName": "exit_transition_duration_ms",
            "affinity": "INTEGER"
          },
          {
            "fieldPath": "contentMode",
            "columnName": "content_mode",
            "affinity": "TEXT",
            "notNull": true
          },
          {
            "fieldPath": "volume",
            "columnName": "volume",
            "affinity": "REAL",
            "notNull": true
          },
          {
            "fieldPath": "speed",
            "columnName": "speed",
            "affinity": "REAL",
            "notNull": true
          },
          {
            "fieldPath": "brightness",
            "columnName": "brightness",
            "affinity": "REAL",
            "notNull": true
          },
          {
            "fieldPath": "contrast",
            "columnName": "contrast",
            "affinity": "REAL",
            "notNull": true
          },
          {
            "fieldPath": "saturation",
            "columnName": "saturation",
            "affinity": "REAL",
            "notNull": true
          },
          {
            "fieldPath": "rotation",
            "columnName": "rotation",
            "affinity": "REAL",
            "notNull": true
          },
          {
            "fieldPath": "scale",
            "columnName": "scale",
            "affinity": "REAL",
            "notNull": true
          },
          {
            "fieldPath": "positionX",
            "columnName": "position_x",
            "affinity": "REAL",
            "notNull": true
          },
          {
            "fieldPath": "positionY",
            "columnName": "position_y",
            "affinity": "REAL",
            "notNull": true
          },
          {
            "fieldPath": "opacity",
            "columnName": "opacity",
            "affinity": "REAL",
            "notNull": true
          }
        ],
        "primaryKey": {
          "autoGenerate": false,
          "columnNames": [
            "id"
          ]
        },
        "indices": [
          {
            "name": "index_timeline_clips_track_id",
            "unique": false,
            "columnNames": [
              "track_id"
            ],
            "orders": [],
            "createSql": "CREATE INDEX IF NOT EXISTS `index_timeline_clips_track_id` ON `${TABLE_NAME}` (`track_id`)"
          }
        ],
        "foreignKeys": [
          {
            "table": "timeline_tracks",
            "onDelete": "CASCADE",
            "onUpdate": "NO ACTION",
            "columns": [
              "track_id"
            ],
            "referencedColumns": [
              "id"
            ]
          }
        ]
      },
      {
        "tableName": "overlays",
        "createSql": "CREATE TABLE IF NOT EXISTS `${TABLE_NAME}` (`id` TEXT NOT NULL, `project_id` TEXT NOT NULL, `timeline_clip_id` TEXT NOT NULL, `name` TEXT NOT NULL, `overlay_type` TEXT NOT NULL, `position_x` REAL NOT NULL, `position_y` REAL NOT NULL, `anchor` TEXT NOT NULL, `size_width` REAL NOT NULL, `size_height` REAL NOT NULL, `style_json` TEXT NOT NULL, `config_json` TEXT NOT NULL, PRIMARY KEY(`id`), FOREIGN KEY(`project_id`) REFERENCES `projects`(`id`) ON UPDATE NO ACTION ON DELETE CASCADE )",
        "fields": [
          {
            "fieldPath": "id",
            "columnName": "id",
            "affinity": "TEXT",
            "notNull": true
          },
          {
            "fieldPath": "projectId",
            "columnName": "project_id",
            "affinity": "TEXT",
            "notNull": true
          },
          {
            "fieldPath": "timelineClipId",
            "columnName": "timeline_clip_id",
            "affinity": "TEXT",
            "notNull": true
          },
          {
            "fieldPath": "name",
            "columnName": "name",
            "affinity": "TEXT",
            "notNull": true
          },
          {
            "fieldPath": "overlayType",
            "columnName": "overlay_type",
            "affinity": "TEXT",
            "notNull": true
          },
          {
            "fieldPath": "positionX",
            "columnName": "position_x",
            "affinity": "REAL",
            "notNull": true
          },
          {
            "fieldPath": "positionY",
            "columnName": "position_y",
            "affinity": "REAL",
            "notNull": true
          },
          {
            "fieldPath": "anchor",
            "columnName": "anchor",
            "affinity": "TEXT",
            "notNull": true
          },
          {
            "fieldPath": "sizeWidth",
            "columnName": "size_width",
            "affinity": "REAL",
            "notNull": true
          },
          {
            "fieldPath": "sizeHeight",
            "columnName": "size_height",
            "affinity": "REAL",
            "notNull": true
          },
          {
            "fieldPath": "styleJson",
            "columnName": "style_json",
            "affinity": "TEXT",
            "notNull": true
          },
          {
            "fieldPath": "configJson",
            "columnName": "config_json",
            "affinity": "TEXT",
            "notNull": true
          }
        ],
        "primaryKey": {
          "autoGenerate": false,
          "columnNames": [
            "id"
          ]
        },
        "indices": [
          {
            "name": "index_overlays_project_id",
            "unique": false,
            "columnNames": [
              "project_id"
            ],
            "orders": [],
            "createSql": "CREATE INDEX IF NOT EXISTS `index_overlays_project_id` ON `${TABLE_NAME}` (`project_id`)"
          }
        ],
        "foreignKeys": [
          {
            "table": "projects",
            "onDelete": "CASCADE",
            "onUpdate": "NO ACTION",
            "columns": [
              "project_id"
            ],
            "referencedColumns": [
              "id"
            ]
          }
        ]
      },
      {
        "tableName": "templates",
        "createSql": "CREATE TABLE IF NOT EXISTS `${TABLE_NAME}` (`id` TEXT NOT NULL, `name` TEXT NOT NULL, `description` TEXT, `sport_type` TEXT, `thumbnail_path` TEXT, `is_built_in` INTEGER NOT NULL, `created_at` INTEGER NOT NULL, `track_layout_json` TEXT NOT NULL, `overlay_presets_json` TEXT NOT NULL, `output_settings_json` TEXT NOT NULL, `style_preset_json` TEXT NOT NULL, PRIMARY KEY(`id`))",
        "fields": [
          {
            "fieldPath": "id",
            "columnName": "id",
            "affinity": "TEXT",
            "notNull": true
          },
          {
            "fieldPath": "name",
            "columnName": "name",
            "affinity": "TEXT",
            "notNull": true
          },
          {
            "fieldPath": "description",
            "columnName": "description",
            "affinity": "TEXT"
          },
          {
            "fieldPath": "sportType",
            "columnName": "sport_type",
            "affinity": "TEXT"
          },
          {
            "fieldPath": "thumbnailPath",
            "columnName": "thumbnail_path",
            "affinity": "TEXT"
          },
          {
            "fieldPath": "isBuiltIn",
            "columnName": "is_built_in",
            "affinity": "INTEGER",
            "notNull": true
          },
          {
            "fieldPath": "createdAt",
            "columnName": "created_at",
            "affinity": "INTEGER",
            "notNull": true
          },
          {
            "fieldPath": "trackLayoutJson",
            "columnName": "track_layout_json",
            "affinity": "TEXT",
            "notNull": true
          },
          {
            "fieldPath": "overlayPresetsJson",
            "columnName": "overlay_presets_json",
            "affinity": "TEXT",
            "notNull": true
          },
          {
            "fieldPath": "outputSettingsJson",
            "columnName": "output_settings_json",
            "affinity": "TEXT",
            "notNull": true
          },
          {
            "fieldPath": "stylePresetJson",
            "columnName": "style_preset_json",
            "affinity": "TEXT",
            "notNull": true
          }
        ],
        "primaryKey": {
          "autoGenerate": false,
          "columnNames": [
            "id"
          ]
        }
      }
    ],
    "setupQueries": [
      "CREATE TABLE IF NOT EXISTS room_master_table (id INTEGER PRIMARY KEY,identity_hash TEXT)",
      "INSERT OR REPLACE INTO room_master_table (id,identity_hash) VALUES(42, 'c362960db95b2ae4034c3ac082d47e47')"
    ]
  }
}